# 2013.08.22 22:13:42 Pacific Daylight Time
# Embedded file name: _strptime
import time
import locale
import calendar
from re import compile as re_compile
from re import IGNORECASE
from re import escape as re_escape
from datetime import date as datetime_date
try:
    from thread import allocate_lock as _thread_allocate_lock
except:
    from dummy_thread import allocate_lock as _thread_allocate_lock

__author__ = 'Brett Cannon'
__email__ = 'brett@python.org'
__all__ = ['strptime']

def _getlang():
    return locale.getlocale(locale.LC_TIME)


class LocaleTime(object):
    __module__ = __name__

    def __init__(self):
        self.lang = _getlang()
        self.__calc_weekday()
        self.__calc_month()
        self.__calc_am_pm()
        self.__calc_timezone()
        self.__calc_date_time()
        if _getlang() != self.lang:
            raise ValueError('locale changed during initialization')

    def __pad(self, seq, front):
        seq = list(seq)
        if front:
            seq.insert(0, '')
        else:
            seq.append('')
        return seq

    def __calc_weekday(self):
        a_weekday = [ calendar.day_abbr[i].lower() for i in range(7) ]
        f_weekday = [ calendar.day_name[i].lower() for i in range(7) ]
        self.a_weekday = a_weekday
        self.f_weekday = f_weekday

    def __calc_month(self):
        a_month = [ calendar.month_abbr[i].lower() for i in range(13) ]
        f_month = [ calendar.month_name[i].lower() for i in range(13) ]
        self.a_month = a_month
        self.f_month = f_month

    def __calc_am_pm(self):
        am_pm = []
        for hour in (1, 22):
            time_tuple = time.struct_time((1999,
             3,
             17,
             hour,
             44,
             55,
             2,
             76,
             0))
            am_pm.append(time.strftime('%p', time_tuple).lower())

        self.am_pm = am_pm

    def __calc_date_time(self):
        time_tuple = time.struct_time((1999, 3, 17, 22, 44, 55, 2, 76, 0))
        date_time = [None, None, None]
        date_time[0] = time.strftime('%c', time_tuple).lower()
        date_time[1] = time.strftime('%x', time_tuple).lower()
        date_time[2] = time.strftime('%X', time_tuple).lower()
        replacement_pairs = [('%', '%%'),
         (self.f_weekday[2], '%A'),
         (self.f_month[3], '%B'),
         (self.a_weekday[2], '%a'),
         (self.a_month[3], '%b'),
         (self.am_pm[1], '%p'),
         ('1999', '%Y'),
         ('99', '%y'),
         ('22', '%H'),
         ('44', '%M'),
         ('55', '%S'),
         ('76', '%j'),
         ('17', '%d'),
         ('03', '%m'),
         ('3', '%m'),
         ('2', '%w'),
         ('10', '%I')]
        replacement_pairs.extend([ (tz, '%Z') for tz_values in self.timezone for tz in tz_values ])
        for offset, directive in ((0, '%c'), (1, '%x'), (2, '%X')):
            current_format = date_time[offset]
            for old, new in replacement_pairs:
                if old:
                    current_format = current_format.replace(old, new)

            time_tuple = time.struct_time((1999, 1, 3, 1, 1, 1, 6, 3, 0))
            if time.strftime(directive, time_tuple).find('00'):
                U_W = '%U'
            else:
                U_W = '%W'
            date_time[offset] = current_format.replace('11', U_W)

        self.LC_date_time = date_time[0]
        self.LC_date = date_time[1]
        self.LC_time = date_time[2]
        return

    def __calc_timezone(self):
        try:
            time.tzset()
        except AttributeError:
            pass

        no_saving = frozenset(['utc', 'gmt', time.tzname[0].lower()])
        if time.daylight:
            has_saving = frozenset([time.tzname[1].lower()])
        else:
            has_saving = frozenset()
        self.timezone = (no_saving, has_saving)


class TimeRE(dict):
    __module__ = __name__

    def __init__--- This code section failed: ---

0	LOAD_FAST         'locale_time'
3	JUMP_IF_FALSE     '18'

6	LOAD_FAST         'locale_time'
9	LOAD_FAST         'self'
12	STORE_ATTR        'locale_time'
15	JUMP_FORWARD      '30'

18	LOAD_GLOBAL       'LocaleTime'
21	CALL_FUNCTION_0   None
24	LOAD_FAST         'self'
27	STORE_ATTR        'locale_time'
30_0	COME_FROM         '15'

30	LOAD_GLOBAL       'super'
33	LOAD_GLOBAL       'TimeRE'
36	LOAD_FAST         'self'
39	CALL_FUNCTION_2   None
42	STORE_FAST        'base'

45	LOAD_FAST         'base'
48	LOAD_ATTR         '__init__'
51	BUILD_MAP         None
54	DUP_TOP           None
55	LOAD_CONST        'd'
58	LOAD_CONST        '(?P<d>3[0-1]|[1-2]\\d|0[1-9]|[1-9]| [1-9])'
61	ROT_THREE         None
62	STORE_SUBSCR      None
63	DUP_TOP           None
64	LOAD_CONST        'H'
67	LOAD_CONST        '(?P<H>2[0-3]|[0-1]\\d|\\d)'
70	ROT_THREE         None
71	STORE_SUBSCR      None
72	DUP_TOP           None
73	LOAD_CONST        'I'
76	LOAD_CONST        '(?P<I>1[0-2]|0[1-9]|[1-9])'
79	ROT_THREE         None
80	STORE_SUBSCR      None
81	DUP_TOP           None
82	LOAD_CONST        'j'
85	LOAD_CONST        '(?P<j>36[0-6]|3[0-5]\\d|[1-2]\\d\\d|0[1-9]\\d|00[1-9]|[1-9]\\d|0[1-9]|[1-9])'
88	ROT_THREE         None
89	STORE_SUBSCR      None
90	DUP_TOP           None
91	LOAD_CONST        'm'
94	LOAD_CONST        '(?P<m>1[0-2]|0[1-9]|[1-9])'
97	ROT_THREE         None
98	STORE_SUBSCR      None
99	DUP_TOP           None
100	LOAD_CONST        'M'
103	LOAD_CONST        '(?P<M>[0-5]\\d|\\d)'
106	ROT_THREE         None
107	STORE_SUBSCR      None
108	DUP_TOP           None
109	LOAD_CONST        'S'
112	LOAD_CONST        '(?P<S>6[0-1]|[0-5]\\d|\\d)'
115	ROT_THREE         None
116	STORE_SUBSCR      None
117	DUP_TOP           None
118	LOAD_CONST        'U'
121	LOAD_CONST        '(?P<U>5[0-3]|[0-4]\\d|\\d)'
124	ROT_THREE         None
125	STORE_SUBSCR      None
126	DUP_TOP           None
127	LOAD_CONST        'w'
130	LOAD_CONST        '(?P<w>[0-6])'
133	ROT_THREE         None
134	STORE_SUBSCR      None
135	DUP_TOP           None
136	LOAD_CONST        'y'
139	LOAD_CONST        '(?P<y>\\d\\d)'
142	ROT_THREE         None
143	STORE_SUBSCR      None
144	DUP_TOP           None
145	LOAD_CONST        'Y'
148	LOAD_CONST        '(?P<Y>\\d\\d\\d\\d)'
151	ROT_THREE         None
152	STORE_SUBSCR      None
153	DUP_TOP           None
154	LOAD_CONST        'A'
157	LOAD_FAST         'self'
160	LOAD_ATTR         '__seqToRE'
163	LOAD_FAST         'self'
166	LOAD_ATTR         'locale_time'
169	LOAD_ATTR         'f_weekday'
172	LOAD_CONST        'A'
175	CALL_FUNCTION_2   None
178	ROT_THREE         None
179	STORE_SUBSCR      None
180	DUP_TOP           None
181	LOAD_CONST        'a'
184	LOAD_FAST         'self'
187	LOAD_ATTR         '__seqToRE'
190	LOAD_FAST         'self'
193	LOAD_ATTR         'locale_time'
196	LOAD_ATTR         'a_weekday'
199	LOAD_CONST        'a'
202	CALL_FUNCTION_2   None
205	ROT_THREE         None
206	STORE_SUBSCR      None
207	DUP_TOP           None
208	LOAD_CONST        'B'
211	LOAD_FAST         'self'
214	LOAD_ATTR         '__seqToRE'
217	LOAD_FAST         'self'
220	LOAD_ATTR         'locale_time'
223	LOAD_ATTR         'f_month'
226	LOAD_CONST        1
229	SLICE+1           None
230	LOAD_CONST        'B'
233	CALL_FUNCTION_2   None
236	ROT_THREE         None
237	STORE_SUBSCR      None
238	DUP_TOP           None
239	LOAD_CONST        'b'
242	LOAD_FAST         'self'
245	LOAD_ATTR         '__seqToRE'
248	LOAD_FAST         'self'
251	LOAD_ATTR         'locale_time'
254	LOAD_ATTR         'a_month'
257	LOAD_CONST        1
260	SLICE+1           None
261	LOAD_CONST        'b'
264	CALL_FUNCTION_2   None
267	ROT_THREE         None
268	STORE_SUBSCR      None
269	DUP_TOP           None
270	LOAD_CONST        'p'
273	LOAD_FAST         'self'
276	LOAD_ATTR         '__seqToRE'
279	LOAD_FAST         'self'
282	LOAD_ATTR         'locale_time'
285	LOAD_ATTR         'am_pm'
288	LOAD_CONST        'p'
291	CALL_FUNCTION_2   None
294	ROT_THREE         None
295	STORE_SUBSCR      None
296	DUP_TOP           None
297	LOAD_CONST        'Z'
300	LOAD_FAST         'self'
303	LOAD_ATTR         '__seqToRE'
306	LOAD_CONST        '<code_object <generator expression>>'
309	MAKE_FUNCTION_0   None
312	LOAD_FAST         'self'
315	LOAD_ATTR         'locale_time'
318	LOAD_ATTR         'timezone'
321	GET_ITER          None
322	CALL_FUNCTION_1   None

325	LOAD_CONST        'Z'
328	CALL_FUNCTION_2   None
331	ROT_THREE         None
332	STORE_SUBSCR      None
333	DUP_TOP           None
334	LOAD_CONST        '%'
337	LOAD_CONST        '%'
340	ROT_THREE         None
341	STORE_SUBSCR      None
342	CALL_FUNCTION_1   None
345	POP_TOP           None

346	LOAD_FAST         'base'
349	LOAD_ATTR         '__setitem__'
352	LOAD_CONST        'W'
355	LOAD_FAST         'base'
358	LOAD_ATTR         '__getitem__'
361	LOAD_CONST        'U'
364	CALL_FUNCTION_1   None
367	LOAD_ATTR         'replace'
370	LOAD_CONST        'U'
373	LOAD_CONST        'W'
376	CALL_FUNCTION_2   None
379	CALL_FUNCTION_2   None
382	POP_TOP           None

383	LOAD_FAST         'base'
386	LOAD_ATTR         '__setitem__'
389	LOAD_CONST        'c'
392	LOAD_FAST         'self'
395	LOAD_ATTR         'pattern'
398	LOAD_FAST         'self'
401	LOAD_ATTR         'locale_time'
404	LOAD_ATTR         'LC_date_time'
407	CALL_FUNCTION_1   None
410	CALL_FUNCTION_2   None
413	POP_TOP           None

414	LOAD_FAST         'base'
417	LOAD_ATTR         '__setitem__'
420	LOAD_CONST        'x'
423	LOAD_FAST         'self'
426	LOAD_ATTR         'pattern'
429	LOAD_FAST         'self'
432	LOAD_ATTR         'locale_time'
435	LOAD_ATTR         'LC_date'
438	CALL_FUNCTION_1   None
441	CALL_FUNCTION_2   None
444	POP_TOP           None

445	LOAD_FAST         'base'
448	LOAD_ATTR         '__setitem__'
451	LOAD_CONST        'X'
454	LOAD_FAST         'self'
457	LOAD_ATTR         'pattern'
460	LOAD_FAST         'self'
463	LOAD_ATTR         'locale_time'
466	LOAD_ATTR         'LC_time'
469	CALL_FUNCTION_1   None
472	CALL_FUNCTION_2   None
475	POP_TOP           None

Syntax error at or near `MAKE_FUNCTION_0' token at offset 309

    def __seqToRE--- This code section failed: ---

0	LOAD_GLOBAL       'sorted'
3	LOAD_FAST         'to_convert'
6	LOAD_CONST        'key'
9	LOAD_GLOBAL       'len'
12	LOAD_CONST        'reverse'
15	LOAD_GLOBAL       'True'
18	CALL_FUNCTION_513 None
21	STORE_FAST        'to_convert'

24	SETUP_LOOP        '61'
27	LOAD_FAST         'to_convert'
30	GET_ITER          None
31	FOR_ITER          '56'
34	STORE_FAST        'value'

37	LOAD_FAST         'value'
40	LOAD_CONST        ''
43	COMPARE_OP        '!='
46	JUMP_IF_FALSE     '53'

49	BREAK_LOOP        None
50	JUMP_BACK         '31'
53	JUMP_BACK         '31'
56	POP_BLOCK         None

57	LOAD_CONST        ''
60	RETURN_VALUE      None
61_0	COME_FROM         '24'

61	LOAD_CONST        '|'
64	LOAD_ATTR         'join'
67	LOAD_CONST        '<code_object <generator expression>>'
70	MAKE_FUNCTION_0   None
73	LOAD_FAST         'to_convert'
76	GET_ITER          None
77	CALL_FUNCTION_1   None
80	CALL_FUNCTION_1   None
83	STORE_FAST        'regex'

86	LOAD_CONST        '(?P<%s>%s'
89	LOAD_FAST         'directive'
92	LOAD_FAST         'regex'
95	BUILD_TUPLE_2     None
98	BINARY_MODULO     None
99	STORE_FAST        'regex'

102	LOAD_CONST        '%s)'
105	LOAD_FAST         'regex'
108	BINARY_MODULO     None
109	RETURN_VALUE      None
-1	RETURN_LAST       None

Syntax error at or near `LOAD_FAST' token at offset 73

    def pattern(self, format):
        processed_format = ''
        regex_chars = re_compile('([\\\\.^$*+?\\(\\){}\\[\\]|])')
        format = regex_chars.sub('\\\\\\1', format)
        whitespace_replacement = re_compile('\\s+')
        format = whitespace_replacement.sub('\\s*', format)
        while '%' in format:
            directive_index = format.index('%') + 1
            processed_format = '%s%s%s' % (processed_format, format[:directive_index - 1], self[format[directive_index]])
            format = format[directive_index + 1:]

        return '%s%s' % (processed_format, format)

    def compile(self, format):
        return re_compile(self.pattern(format), IGNORECASE)


_cache_lock = _thread_allocate_lock()
_TimeRE_cache = TimeRE()
_CACHE_MAX_SIZE = 5
_regex_cache = {}

def strptime(data_string, format = '%a %b %d %H:%M:%S %Y'):
    global _TimeRE_cache
    _cache_lock.acquire()
    try:
        time_re = _TimeRE_cache
        locale_time = time_re.locale_time
        if _getlang() != locale_time.lang:
            _TimeRE_cache = TimeRE()
        if len(_regex_cache) > _CACHE_MAX_SIZE:
            _regex_cache.clear()
        format_regex = _regex_cache.get(format)
        if not format_regex:
            format_regex = time_re.compile(format)
            _regex_cache[format] = format_regex
    finally:
        _cache_lock.release()

    found = format_regex.match(data_string)
    if not found:
        raise ValueError('time data did not match format:  data=%s  fmt=%s' % (data_string, format))
    if len(data_string) != found.end():
        raise ValueError('unconverted data remains: %s' % data_string[found.end():])
    year = 1900
    month = day = 1
    hour = minute = second = 0
    tz = -1
    week_of_year = -1
    week_of_year_start = -1
    weekday = julian = -1
    found_dict = found.groupdict()
    for group_key in found_dict.iterkeys():
        if group_key == 'y':
            year = int(found_dict['y'])
            if year <= 68:
                year += 2000
            else:
                year += 1900
        elif group_key == 'Y':
            year = int(found_dict['Y'])
        elif group_key == 'm':
            month = int(found_dict['m'])
        elif group_key == 'B':
            month = locale_time.f_month.index(found_dict['B'].lower())
        elif group_key == 'b':
            month = locale_time.a_month.index(found_dict['b'].lower())
        elif group_key == 'd':
            day = int(found_dict['d'])
        elif group_key == 'H':
            hour = int(found_dict['H'])
        elif group_key == 'I':
            hour = int(found_dict['I'])
            ampm = found_dict.get('p', '').lower()
            if ampm in ('', locale_time.am_pm[0]):
                if hour == 12:
                    hour = 0
            elif ampm == locale_time.am_pm[1]:
                if hour != 12:
                    hour += 12
        elif group_key == 'M':
            minute = int(found_dict['M'])
        elif group_key == 'S':
            second = int(found_dict['S'])
        elif group_key == 'A':
            weekday = locale_time.f_weekday.index(found_dict['A'].lower())
        elif group_key == 'a':
            weekday = locale_time.a_weekday.index(found_dict['a'].lower())
        elif group_key == 'w':
            weekday = int(found_dict['w'])
            if weekday == 0:
                weekday = 6
            else:
                weekday -= 1
        elif group_key == 'j':
            julian = int(found_dict['j'])
        elif group_key in ('U', 'W'):
            week_of_year = int(found_dict[group_key])
            if group_key == 'U':
                week_of_year_start = 6
            else:
                week_of_year_start = 0
        elif group_key == 'Z':
            found_zone = found_dict['Z'].lower()
            for value, tz_values in enumerate(locale_time.timezone):
                if found_zone in tz_values:
                    if time.tzname[0] == time.tzname[1] and time.daylight and found_zone not in ('utc', 'gmt'):
                        break
                    else:
                        tz = value
                        break

    if julian == -1 and week_of_year != -1 and weekday != -1:
        first_weekday = datetime_date(year, 1, 1).weekday()
        preceeding_days = 7 - first_weekday
        if preceeding_days == 7:
            preceeding_days = 0
        if weekday == 6 and week_of_year_start == 6:
            week_of_year -= 1
        if weekday == 0 and first_weekday == 0 and week_of_year_start == 6:
            week_of_year += 1
        if week_of_year == 0:
            julian = 1 + weekday - first_weekday
        else:
            days_to_week = preceeding_days + 7 * (week_of_year - 1)
            julian = 1 + days_to_week + weekday
    if julian == -1:
        julian = datetime_date(year, month, day).toordinal() - datetime_date(year, 1, 1).toordinal() + 1
    else:
        datetime_result = datetime_date.fromordinal(julian - 1 + datetime_date(year, 1, 1).toordinal())
        year = datetime_result.year
        month = datetime_result.month
        day = datetime_result.day
    if weekday == -1:
        weekday = datetime_date(year, month, day).weekday()
    return time.struct_time((year,
     month,
     day,
     hour,
     minute,
     second,
     weekday,
     julian,
     tz))# decompiled 0 files: 0 okay, 1 failed, 0 verify failed
# 2013.08.22 22:13:42 Pacific Daylight Time

# Can't uncompyle C:\Users\Maverick\Documents\Visual Studio 2010\Projects\Unfreezer\py2\_strptime.pyc
Traceback (most recent call last):
  File "C:\python27\lib\uncompyle2\__init__.py", line 206, in main
    uncompyle_file(infile, outstream, showasm, showast)
  File "C:\python27\lib\uncompyle2\__init__.py", line 143, in uncompyle_file
    uncompyle(version, co, outstream, showasm, showast)
  File "C:\python27\lib\uncompyle2\__init__.py", line 132, in uncompyle
    raise walk.ERROR
ParserError: --- This code section failed: ---

0	LOAD_GLOBAL       'sorted'
3	LOAD_FAST         'to_convert'
6	LOAD_CONST        'key'
9	LOAD_GLOBAL       'len'
12	LOAD_CONST        'reverse'
15	LOAD_GLOBAL       'True'
18	CALL_FUNCTION_513 None
21	STORE_FAST        'to_convert'

24	SETUP_LOOP        '61'
27	LOAD_FAST         'to_convert'
30	GET_ITER          None
31	FOR_ITER          '56'
34	STORE_FAST        'value'

37	LOAD_FAST         'value'
40	LOAD_CONST        ''
43	COMPARE_OP        '!='
46	JUMP_IF_FALSE     '53'

49	BREAK_LOOP        None
50	JUMP_BACK         '31'
53	JUMP_BACK         '31'
56	POP_BLOCK         None

57	LOAD_CONST        ''
60	RETURN_VALUE      None
61_0	COME_FROM         '24'

61	LOAD_CONST        '|'
64	LOAD_ATTR         'join'
67	LOAD_CONST        '<code_object <generator expression>>'
70	MAKE_FUNCTION_0   None
73	LOAD_FAST         'to_convert'
76	GET_ITER          None
77	CALL_FUNCTION_1   None
80	CALL_FUNCTION_1   None
83	STORE_FAST        'regex'

86	LOAD_CONST        '(?P<%s>%s'
89	LOAD_FAST         'directive'
92	LOAD_FAST         'regex'
95	BUILD_TUPLE_2     None
98	BINARY_MODULO     None
99	STORE_FAST        'regex'

102	LOAD_CONST        '%s)'
105	LOAD_FAST         'regex'
108	BINARY_MODULO     None
109	RETURN_VALUE      None
-1	RETURN_LAST       None

Syntax error at or near `LOAD_FAST' token at offset 73

